savepip/__init__.py
savepip/cli.py
savepip/core.py
savepip/memory_manager.py
savepip-0.2.0.dist-info/licenses/LICENSE
savepip-0.2.0.dist-info/METADATA
savepip-0.2.0.dist-info/WHEEL
savepip-0.2.0.dist-info/entry_points.txt
savepip-0.2.0.dist-info/top_level.txt
savepip-0.2.0.dist-info/RECORD
