Metadata-Version: 2.4
Name: savepip
Version: 0.2.0
Summary: A tool to install and save clean package dependencies
Home-page: https://github.com/Aeidle/savepip
Author: ADIL ALAMI
Author-email: adilalami707@gmail.com
Classifier: Programming Language :: Python :: 3
Classifier: License :: OSI Approved :: MIT License
Classifier: Operating System :: OS Independent
Requires-Python: >=3.6
License-File: LICENSE
Requires-Dist: pyyaml>=5.1
Dynamic: author
Dynamic: author-email
Dynamic: classifier
Dynamic: description
Dynamic: description-content-type
Dynamic: home-page
Dynamic: license-file
Dynamic: requires-dist
Dynamic: requires-python
Dynamic: summary
